MANIFEST.in
README.rst
setup.py
pycdb/__init__.py
pycdb/_pycdb.c
pycdb/_pycdb.pyx
pycdb/alloc.c
pycdb/alloc.h
pycdb/buffer.c
pycdb/buffer.h
pycdb/buffer_2.c
pycdb/buffer_put.c
pycdb/byte.h
pycdb/byte_copy.c
pycdb/byte_cr.c
pycdb/byte_diff.c
pycdb/cdb.c
pycdb/cdb.h
pycdb/cdb_hash.c
pycdb/cdb_make.c
pycdb/cdb_make.h
pycdb/error.c
pycdb/error.h
pycdb/error_str.c
pycdb/fmt.h
pycdb/fmt_ulong.c
pycdb/readwrite.h
pycdb/scan.h
pycdb/scan_ulong.c
pycdb/seek.h
pycdb/seek_cur.c
pycdb/seek_set.c
pycdb/str.h
pycdb/str_len.c
pycdb/tests.py
pycdb/uint32.h
pycdb/uint32_pack.c
pycdb/uint32_unpack.c
pycdb.egg-info/PKG-INFO
pycdb.egg-info/SOURCES.txt
pycdb.egg-info/dependency_links.txt
pycdb.egg-info/not-zip-safe
pycdb.egg-info/top_level.txt