Metadata-Version: 1.1
Name: pycdb
Version: 0.0.1
Summary: Yet another CDB wrapper
Home-page: http://github.com/moriyoshi/pycdb
Author: Moriyoshi Koizumi
Author-email: mozo@mozo.jp
License: public domain
Keywords: cdb,cython
Platform: UNKNOWN
Classifier: Programming Language :: Python
Classifier: Programming Language :: Python :: 2
Classifier: Programming Language :: Python :: 3
Classifier: Development Status :: 5 - Production/Stable
Classifier: Intended Audience :: Developers
Classifier: Topic :: Database
Classifier: License :: Public Domain
